owidPy/__init__.py
owidPy-0.0.7.dist-info/LICENSE
owidPy-0.0.7.dist-info/METADATA
owidPy-0.0.7.dist-info/WHEEL
owidPy-0.0.7.dist-info/top_level.txt
owidPy-0.0.7.dist-info/RECORD
