Metadata-Version: 2.1
Name: owidPy
Version: 0.0.7
Summary: Python Package for importing data from Our World in Data
Home-page: UNKNOWN
Author: Piers York
Author-email: <piers.york@gmail.com>
License: UNKNOWN
Keywords: python,Our World in Data
Platform: UNKNOWN
Classifier: Development Status :: 3 - Alpha
Classifier: Intended Audience :: Education
Classifier: Programming Language :: Python :: 2
Classifier: Programming Language :: Python :: 3
Classifier: Operating System :: MacOS :: MacOS X
Classifier: Operating System :: Microsoft :: Windows
